wechatpush.py
py_WechatPush-0.1.5.dist-info/LICENSE
py_WechatPush-0.1.5.dist-info/METADATA
py_WechatPush-0.1.5.dist-info/WHEEL
py_WechatPush-0.1.5.dist-info/top_level.txt
py_WechatPush-0.1.5.dist-info/RECORD
