Metadata-Version: 2.1
Name: py-WechatPush
Version: 0.1.5
Summary: A Python WeChat official account push library
Home-page: https://wechatpush.danke.ml
Author: DanKe
Author-email: danke1024@foxmail.com
License: MIT
Classifier: License :: OSI Approved :: MIT License
Classifier: Programming Language :: Python
Classifier: Programming Language :: Python :: 3
Classifier: Programming Language :: Python :: 3.6
Classifier: Programming Language :: Python :: Implementation :: CPython
Classifier: Programming Language :: Python :: Implementation :: PyPy
Requires-Python: >=3
License-File: LICENSE
Requires-Dist: requests
